wedeliver_core_plus/__init__.py
wedeliver_core_plus/base.py
wedeliver_core_plus/app_decorators/__init__.py
wedeliver_core_plus/app_decorators/app_entry.py
wedeliver_core_plus/app_decorators/handle_auth.py
wedeliver_core_plus/app_decorators/handle_exceptions.py
wedeliver_core_plus/app_decorators/handle_response.py
wedeliver_core_plus/app_decorators/serializer.py
wedeliver_core_plus/helpers/__init__.py
wedeliver_core_plus/helpers/acl_enum.py
wedeliver_core_plus/helpers/atomic_transactions.py
wedeliver_core_plus/helpers/atomic_transactions_v2.py
wedeliver_core_plus/helpers/auth.py
wedeliver_core_plus/helpers/authenticate.py
wedeliver_core_plus/helpers/config.py
wedeliver_core_plus/helpers/enums.py
wedeliver_core_plus/helpers/exceptions.py
wedeliver_core_plus/helpers/fetch_relational_data.py
wedeliver_core_plus/helpers/filters.py
wedeliver_core_plus/helpers/format_exception.py
wedeliver_core_plus/helpers/get_callback.py
wedeliver_core_plus/helpers/get_country_code.py
wedeliver_core_plus/helpers/get_embedded_function.py
wedeliver_core_plus/helpers/get_obj_value.py
wedeliver_core_plus/helpers/get_prefix.py
wedeliver_core_plus/helpers/hmac_validator.py
wedeliver_core_plus/helpers/kafka_listener.py
wedeliver_core_plus/helpers/kafka_producer.py
wedeliver_core_plus/helpers/log_config.py
wedeliver_core_plus/helpers/micro_fetcher.py
wedeliver_core_plus/helpers/model_discovery.py
wedeliver_core_plus/helpers/numbers.py
wedeliver_core_plus/helpers/raise_exception_in_background.py
wedeliver_core_plus/helpers/search_function.py
wedeliver_core_plus/helpers/security.py
wedeliver_core_plus/helpers/service_config.py
wedeliver_core_plus/helpers/sql.py
wedeliver_core_plus/helpers/system_roles.py
wedeliver_core_plus/helpers/time.py
wedeliver_core_plus/helpers/token_service.py
wedeliver_core_plus/helpers/topics.py
wedeliver_core_plus/helpers/translation.py
wedeliver_core_plus/helpers/validate_mobile_number.py
wedeliver_core_plus/helpers/validate_parameters.py
wedeliver_core_plus-0.8.9.dist-info/METADATA
wedeliver_core_plus-0.8.9.dist-info/WHEEL
wedeliver_core_plus-0.8.9.dist-info/top_level.txt
wedeliver_core_plus-0.8.9.dist-info/RECORD
