Metadata-Version: 2.1
Name: wedeliver-core-plus
Version: 0.8.9
Summary: wedeliver_core_plus package
Home-page: https://thrivve.me/
Author: Iyad Alfarra
Author-email: info@thrivve.me
License: MIT
Classifier: Development Status :: 4 - Beta
Classifier: Intended Audience :: Developers
Classifier: Topic :: Internet
Classifier: License :: OSI Approved :: MIT License
Classifier: Programming Language :: Python
Classifier: Programming Language :: Python :: 3
Classifier: Programming Language :: Python :: 3.3
Classifier: Programming Language :: Python :: 3.4
Classifier: Programming Language :: Python :: 3.5
Classifier: Programming Language :: Python :: 3.6
Requires-Dist: SQLAlchemy
Requires-Dist: Flask-SQLAlchemy
Requires-Dist: flask-marshmallow
Requires-Dist: confluent-kafka
Requires-Dist: requests
Requires-Dist: python-dotenv
